jammer/__init__.py
jammer/chain.py
jammer/helpers.py
jammer/jammer.py
jammer-0.1.dist-info/LICENSE
jammer-0.1.dist-info/METADATA
jammer-0.1.dist-info/WHEEL
jammer-0.1.dist-info/top_level.txt
jammer-0.1.dist-info/RECORD
