Metadata-Version: 2.1
Name: jammer
Version: 0.1
Summary: Library for jax based affine-invariant MCMC sampling
Home-page: https://github.com/utkarshgiri/jammer
Author: Utkarsh Giri
Author-email: utkarshgiri@gmail.com
License: MIT License
Project-URL: Bug Tracker, https://github.com/utkarshgiri/jammer/issues
Keywords: jax,MCMC,affine-invariant,goodman-weare,sampler
Platform: UNKNOWN
Requires-Python: >=3.6
Requires-Dist: jax (>=0.2.12)
Requires-Dist: jaxlib (>=0.1.64)
Requires-Dist: absl-py (>=0.12.0)
Requires-Dist: numpy (>=1.18)
Requires-Dist: tqdm (>=4.50)
Requires-Dist: joblib (>=0.17)
Requires-Dist: matplotlib (>=3.3)
Requires-Dist: corner (>=2.2)
Requires-Dist: emcee (>=3.0)
Requires-Dist: scipy (>=1.6.2)
Requires-Dist: kiwisolver (>=1.3.1)
